ziviz/Ziviz.py
ziviz/__init__.py
ziviz/_version.py
ziviz/labextension/package.json
ziviz/labextension/static/261.edb4ad8904e1ba9eed61.js
ziviz/labextension/static/568.60dbf61e8e888a56a459.js
ziviz/labextension/static/747.60f2a6d801b3917356aa.js
ziviz/labextension/static/remoteEntry.be21550f6091040f4b0a.js
ziviz/labextension/static/style.js
ziviz/labextension/static/third-party-licenses.json
ziviz/nbextension/extension.js
ziviz/nbextension/index.js
ziviz/static/viz_types.json
ziviz-0.1.5.data/data/etc/jupyter/nbconfig/notebook.d/ziviz.json
ziviz-0.1.5.data/data/share/jupyter/labextensions/ziviz/install.json
ziviz-0.1.5.data/data/share/jupyter/labextensions/ziviz/package.json
ziviz-0.1.5.data/data/share/jupyter/labextensions/ziviz/static/261.edb4ad8904e1ba9eed61.js
ziviz-0.1.5.data/data/share/jupyter/labextensions/ziviz/static/568.60dbf61e8e888a56a459.js
ziviz-0.1.5.data/data/share/jupyter/labextensions/ziviz/static/747.60f2a6d801b3917356aa.js
ziviz-0.1.5.data/data/share/jupyter/labextensions/ziviz/static/remoteEntry.be21550f6091040f4b0a.js
ziviz-0.1.5.data/data/share/jupyter/labextensions/ziviz/static/style.js
ziviz-0.1.5.data/data/share/jupyter/labextensions/ziviz/static/third-party-licenses.json
ziviz-0.1.5.data/data/share/jupyter/nbextensions/ziviz/extension.js
ziviz-0.1.5.data/data/share/jupyter/nbextensions/ziviz/index.js
ziviz-0.1.5.dist-info/LICENSE.txt
ziviz-0.1.5.dist-info/METADATA
ziviz-0.1.5.dist-info/WHEEL
ziviz-0.1.5.dist-info/top_level.txt
ziviz-0.1.5.dist-info/RECORD
